loger.py
Loggings/Loggings.py
Loggings/__init__.py
Kingly_Loggings-1.0.62.dist-info/LICENSE
Kingly_Loggings-1.0.62.dist-info/METADATA
Kingly_Loggings-1.0.62.dist-info/WHEEL
Kingly_Loggings-1.0.62.dist-info/top_level.txt
Kingly_Loggings-1.0.62.dist-info/RECORD
