Metadata-Version: 2.1
Name: Kingly-Loggings
Version: 1.0.62
Summary: UNKNOWN
Home-page: UNKNOWN
Author: CHK141
Author-email: chk141@139.com
License: UNKNOWN
Platform: UNKNOWN
Classifier: Programming Language :: Python :: 3
Classifier: License :: OSI Approved :: MIT License
Classifier: Operating System :: OS Independent
Requires-Python: >=3
License-File: LICENSE
Requires-Dist: loguru
Requires-Dist: pathlib
